konvigius/CHANGELOG.md
konvigius/MANUAL.md
konvigius/__init__.py
konvigius/__main__.py
konvigius/cli_parser.py
konvigius/configlib.py
konvigius/core/__init__.py
konvigius/core/base.py
konvigius/core/types.py
konvigius/exceptions.py
konvigius/help.py
konvigius/py.typed
konvigius/validators.py
konvigius-0.0.4.dist-info/licenses/LICENSE
konvigius-0.0.4.dist-info/WHEEL
konvigius-0.0.4.dist-info/METADATA
konvigius-0.0.4.dist-info/RECORD
