Metadata-Version: 2.4
Name: konvigius
Version: 0.0.4
Summary: Python library for managing application config objects with validation and a CLI parser included.
Keywords: config,configuration,validation,CLI
Author: Rik Roos, Roos IT Logics
Author-email: Rik Roos, Roos IT Logics <opensource@bytelogic.nl>
License-Expression: MIT
License-File: LICENSE
Classifier: Programming Language :: Python :: 3
Classifier: License :: OSI Approved :: MIT License
Classifier: Operating System :: OS Independent
Requires-Python: >=3.10
Project-URL: Changelog, https://github.com/RikRoos/konvigius/blob/master/src/konvigius/CHANGELOG.md
Project-URL: Documentation, https://github.com/RikRoos/konvigius#readme
Project-URL: Homepage, https://github.com/RikRoos/konvigius
Project-URL: Issues, https://github.com/RikRoos/konvigius/issues
Project-URL: Source, https://github.com/RikRoos/konvigius
